meza/__init__.py
meza/compat.py
meza/convert.py
meza/dbf.py
meza/fntools.py
meza/io.py
meza/process.py
meza/stats.py
meza/typetools.py
meza/unicsv.py
meza-0.47.0.dist-info/LICENSE
meza-0.47.0.dist-info/METADATA
meza-0.47.0.dist-info/WHEEL
meza-0.47.0.dist-info/top_level.txt
meza-0.47.0.dist-info/RECORD
