Metadata-Version: 2.2
Name: meza
Version: 0.47.0
Summary: A Python toolkit for processing tabular data
Home-page: https://github.com/reubano/meza
Download-URL: https://github.com/reubano/meza/archive/v0.47.0.tar.gz
Author: Reuben Cummings
Author-email: reubano@gmail.com
Maintainer: Jason R. Coombs
Maintainer-email: jaraco@jaraco.com
Keywords: meza,A,Python,toolkit,for,processing,tabular,data
Platform: macOS
Platform: Windows
Platform: Linux
Classifier: License :: OSI Approved :: MIT License
Classifier: Development Status :: 4 - Beta
Classifier: Natural Language :: English
Classifier: Programming Language :: Python :: 3
Classifier: Programming Language :: Python :: 3 :: Only
Classifier: Programming Language :: Python :: Implementation :: CPython
Classifier: Programming Language :: Python :: Implementation :: PyPy
Classifier: Environment :: Console
Classifier: Topic :: Software Development :: Libraries :: Python Modules
Classifier: Intended Audience :: Developers
Classifier: Operating System :: POSIX :: Linux
Classifier: Operating System :: MacOS :: MacOS X
Classifier: Operating System :: Microsoft :: Windows
Requires-Python: >=3.8
License-File: LICENSE
Requires-Dist: chardet<4.0.0,>=3.0.4
Requires-Dist: python-slugify<2.0.0,>=1.2.5
Requires-Dist: python-dateutil<3.0.0,>=2.7.2
Requires-Dist: requests<3.0.0,>=2.18.4
Requires-Dist: xlrd<2.0.0,>=1.1.0
Requires-Dist: dbfread==2.0.4
Requires-Dist: ijson<3.0.0,>=2.3
Requires-Dist: beautifulsoup4<5.0.0,>=4.6.0
Requires-Dist: PyYAML<7.0.0,>=4.2b1
Requires-Dist: pygogo<2.0.0,>=0.13.2
Dynamic: author
Dynamic: author-email
Dynamic: classifier
Dynamic: description
Dynamic: download-url
Dynamic: home-page
Dynamic: keywords
Dynamic: platform
Dynamic: requires-dist
Dynamic: summary
